dcs_code_injector/__init__.py
dcs_code_injector/app.py
dcs_code_injector/code_editor.py
dcs_code_injector/constants.py
dcs_code_injector/dcs_code_injector_window.py
dcs_code_injector/favorites.py
dcs_code_injector/hook_string.py
dcs_code_injector/log_highlighter.py
dcs_code_injector/log_view.py
dcs_code_injector/logger.py
dcs_code_injector/lua_function_parser.py
dcs_code_injector/lua_syntax_highlighter.py
dcs_code_injector/server.py
dcs_code_injector/settings_dialog.py
dcs_code_injector/utils.py
dcs_code_injector/version_dialog.py
dcs_code_injector/versioner.py
dcs_code_injector/ui/__init__.py
dcs_code_injector/ui/dcs_code_injector_search_ui.py
dcs_code_injector/ui/dcs_code_injector_settings_ui.py
dcs_code_injector/ui/dcs_code_injector_window_ui.py
dcs_code_injector/ui/icons/__init__.py
dcs_code_injector/ui/icons/cloud_done.png
dcs_code_injector/ui/icons/cloud_off.png
dcs_code_injector/ui/icons/icon.png
dcs_code_injector/ui/icons/logo.png
dcs_code_injector/ui/splashscreens/__init__.py
dcs_code_injector/ui/splashscreens/splash_01.png
dcs_code_injector/ui/splashscreens/splash_02.png
dcs_code_injector/ui/splashscreens/splash_03.png
dcs_code_injector/ui/splashscreens/splash_04.png
dcs_code_injector/ui/splashscreens/splash_05.png
dcs_code_injector/ui/splashscreens/splash_06.png
dcs_code_injector/ui/splashscreens/splash_07.png
dcs_code_injector-1.4.11.dist-info/LICENSE
dcs_code_injector-1.4.11.dist-info/METADATA
dcs_code_injector-1.4.11.dist-info/WHEEL
dcs_code_injector-1.4.11.dist-info/entry_points.txt
dcs_code_injector-1.4.11.dist-info/top_level.txt
dcs_code_injector-1.4.11.dist-info/RECORD
