Metadata-Version: 2.1
Name: dcs-code-injector
Version: 1.4.11
Summary: A REPL to use with Digital Combat Simulator to execute code while a mission is running.
Home-page: https://www.github.com/nielsvaes/dcs_code_injector
Author: Niels Vaes
Author-email: nielsvaes@gmail.com
License: GNU v3
Platform: win32
Platform: nt
Platform: Windows
Classifier: License :: OSI Approved :: GNU General Public License v3 (GPLv3)
Classifier: Programming Language :: Python :: 3 :: Only
Classifier: Programming Language :: Python :: 3.9
Classifier: Programming Language :: Python :: 3.10
Classifier: Programming Language :: Python :: 3.11
Classifier: Programming Language :: Python :: 3.12
Classifier: Operating System :: Microsoft :: Windows
Classifier: Operating System :: Microsoft :: Windows :: Windows 10
Classifier: Operating System :: Microsoft :: Windows :: Windows 11
Classifier: Topic :: Games/Entertainment
Classifier: Topic :: Games/Entertainment :: Simulation
Classifier: Topic :: Utilities
Requires-Python: >=3.9
License-File: LICENSE
Requires-Dist: ez-icons
Requires-Dist: PySide6 >6.7.0
Requires-Dist: ez-qt
Requires-Dist: ez-settings
Requires-Dist: ez-utils
Requires-Dist: qt-material
Requires-Dist: pygtail
Requires-Dist: requests
